duoguard_nemo/__init__.py
duoguard_nemo/core.py
duoguard_nemo/generation/__init__.py
duoguard_nemo/generation/openai.py
duoguard_nemo/generation/response.py
duoguard_nemo/guardrails/__init__.py
duoguard_nemo/guardrails/checks.py
duoguard_nemo/guardrails/manager.py
duoguard_nemo/guardrails/multiturn.py
duoguard_nemo/guardrails/regex.py
duoguard_nemo/guardrails/semantic.py
duoguard_nemo/logging/__init__.py
duoguard_nemo/logging/logger.py
duoguard_nemo/logging/security.py
duoguard_nemo-0.1.0.dist-info/licenses/LICENSE
duoguard_nemo-0.1.0.dist-info/METADATA
duoguard_nemo-0.1.0.dist-info/WHEEL
duoguard_nemo-0.1.0.dist-info/top_level.txt
duoguard_nemo-0.1.0.dist-info/RECORD
