Metadata-Version: 2.4
Name: duoguard_nemo
Version: 0.1.0
Summary: DuoGuard-Nemo: A multi-layered security system for LLM applications
Author-email: QuillAI Team <team@quillai.ai>
License-Expression: MIT
Requires-Python: >=3.8
License-File: LICENSE
Requires-Dist: openai>=1.0.0
Requires-Dist: nemoguardrails>=0.5.0
Requires-Dist: sentence-transformers>=2.2.2
Requires-Dist: numpy>=1.21.0
Requires-Dist: pydantic>=2.0.0
Requires-Dist: python-dotenv>=1.0.0
Requires-Dist: PyYAML>=6.0.0
Provides-Extra: dev
Requires-Dist: pytest>=7.0.0; extra == "dev"
Requires-Dist: black>=23.0.0; extra == "dev"
Requires-Dist: mypy>=1.0.0; extra == "dev"
Requires-Dist: pytest-asyncio>=0.21.0; extra == "dev"
Dynamic: license-file
